[{"keyword":"Feature","type":"feature","description":"","line":2,"name":"Saucedemo login","uri":"C:\\Users\\Yusuf\\Documents\\HAQIM\\Bootcamp QA\\QA\\wdio_cucumber_ds_batch4\\features\\saucedemo_login.feature","tags":[{"location":{"line":1,"column":1},"name":"@saucedemo","id":"d00b2c75-cb22-4100-86a6-269c4198c8c0"},{"location":{"line":1,"column":12},"name":"@login","id":"1275352f-b79c-4c13-b6a6-ace34f97f6a7"}],"elements":[{"keyword":"Scenario","type":"scenario","description":"","name":"Successful login","tags":[{"name":"@saucedemo","astNodeId":"d00b2c75-cb22-4100-86a6-269c4198c8c0"},{"name":"@login","astNodeId":"1275352f-b79c-4c13-b6a6-ace34f97f6a7"},{"name":"@TC-1","astNodeId":"36d63fe4-8dfb-43be-9a96-0d9a21529788"},{"name":"@TC-2","astNodeId":"d7214667-7a50-4292-8c88-4507bbf92b32"},{"name":"@TC-3","astNodeId":"c0a5b1da-0d73-4a70-a01c-dd1012464efa"},{"name":"@TC-4","astNodeId":"d2437130-47fb-43ad-baf4-fb3a7ca7e427"},{"name":"@standard","astNodeId":"86e20412-6acf-4497-847f-c80e722e69cf"},{"name":"@visual","astNodeId":"3225c49b-9d0c-4b1f-beac-5e986a8fbbd5"},{"name":"@problem_user","astNodeId":"e5dc50f8-c1de-4f26-8e83-64b1b3ea71d6"},{"name":"@performance_glitch_user","astNodeId":"53086390-d4fb-4c4f-bb4d-7e4a07fab550"}],"id":"saucedemo-loginsuccessful-login","steps":[{"arguments":[],"keyword":"Before","name":"","result":{"status":"passed","duration":3000000},"line":null,"match":{"location":"can not be determined with webdriver.io"}},{"arguments":[],"keyword":"Given","name":"user is on Saucedemo login page","result":{"status":"passed","duration":497000000},"line":null,"match":{"location":"can not be determined with webdriver.io"}},{"arguments":[],"keyword":"And","name":"user input password with \"secret_sauce\"","result":{"status":"passed","duration":234000000},"line":null,"match":{"location":"can not be determined with webdriver.io"}},{"arguments":[],"keyword":"Given","name":"user is on Saucedemo login page","result":{"status":"passed","duration":97000000},"line":null,"match":{"location":"can not be determined with webdriver.io"}},{"arguments":[],"keyword":"And","name":"user input username with \"standard_user\"","result":{"status":"passed","duration":231000000},"line":null,"match":{"location":"can not be determined with webdriver.io"}},{"arguments":[],"keyword":"When","name":"user click login button","result":{"status":"passed","duration":37000000},"line":null,"match":{"location":"can not be determined with webdriver.io"}},{"arguments":[],"keyword":"Then","name":"user should redirect to the homepage","result":{"status":"passed","duration":2012000000},"line":null,"match":{"location":"can not be determined with webdriver.io"}},{"arguments":[],"keyword":"After","name":"","result":{"status":"passed","duration":1000000},"line":null,"match":{"location":"can not be determined with webdriver.io"}}]},{"keyword":"Scenario","type":"scenario","description":"","name":"Successful login","tags":[{"name":"@saucedemo","astNodeId":"d00b2c75-cb22-4100-86a6-269c4198c8c0"},{"name":"@login","astNodeId":"1275352f-b79c-4c13-b6a6-ace34f97f6a7"},{"name":"@TC-1","astNodeId":"36d63fe4-8dfb-43be-9a96-0d9a21529788"},{"name":"@TC-2","astNodeId":"d7214667-7a50-4292-8c88-4507bbf92b32"},{"name":"@TC-3","astNodeId":"c0a5b1da-0d73-4a70-a01c-dd1012464efa"},{"name":"@TC-4","astNodeId":"d2437130-47fb-43ad-baf4-fb3a7ca7e427"},{"name":"@standard","astNodeId":"86e20412-6acf-4497-847f-c80e722e69cf"},{"name":"@visual","astNodeId":"3225c49b-9d0c-4b1f-beac-5e986a8fbbd5"},{"name":"@problem_user","astNodeId":"e5dc50f8-c1de-4f26-8e83-64b1b3ea71d6"},{"name":"@performance_glitch_user","astNodeId":"53086390-d4fb-4c4f-bb4d-7e4a07fab550"}],"id":"saucedemo-loginsuccessful-login","steps":[{"arguments":[],"keyword":"Before","name":"","result":{"status":"passed","duration":0},"line":null,"match":{"location":"can not be determined with webdriver.io"}},{"arguments":[],"keyword":"Given","name":"user is on Saucedemo login page","result":{"status":"passed","duration":92000000},"line":null,"match":{"location":"can not be determined with webdriver.io"}},{"arguments":[],"keyword":"And","name":"user input password with \"secret_sauce\"","result":{"status":"passed","duration":225000000},"line":null,"match":{"location":"can not be determined with webdriver.io"}},{"arguments":[],"keyword":"Given","name":"user is on Saucedemo login page","result":{"status":"passed","duration":76000000},"line":null,"match":{"location":"can not be determined with webdriver.io"}},{"arguments":[],"keyword":"And","name":"user input username with \"visual_user\"","result":{"status":"passed","duration":179000000},"line":null,"match":{"location":"can not be determined with webdriver.io"}},{"arguments":[],"keyword":"When","name":"user click login button","result":{"status":"passed","duration":22000000},"line":null,"match":{"location":"can not be determined with webdriver.io"}},{"arguments":[],"keyword":"Then","name":"user should redirect to the homepage","result":{"status":"passed","duration":2016000000},"line":null,"match":{"location":"can not be determined with webdriver.io"}},{"arguments":[],"keyword":"After","name":"","result":{"status":"passed","duration":0},"line":null,"match":{"location":"can not be determined with webdriver.io"}}]},{"keyword":"Scenario","type":"scenario","description":"","name":"Successful login","tags":[{"name":"@saucedemo","astNodeId":"d00b2c75-cb22-4100-86a6-269c4198c8c0"},{"name":"@login","astNodeId":"1275352f-b79c-4c13-b6a6-ace34f97f6a7"},{"name":"@TC-1","astNodeId":"36d63fe4-8dfb-43be-9a96-0d9a21529788"},{"name":"@TC-2","astNodeId":"d7214667-7a50-4292-8c88-4507bbf92b32"},{"name":"@TC-3","astNodeId":"c0a5b1da-0d73-4a70-a01c-dd1012464efa"},{"name":"@TC-4","astNodeId":"d2437130-47fb-43ad-baf4-fb3a7ca7e427"},{"name":"@standard","astNodeId":"86e20412-6acf-4497-847f-c80e722e69cf"},{"name":"@visual","astNodeId":"3225c49b-9d0c-4b1f-beac-5e986a8fbbd5"},{"name":"@problem_user","astNodeId":"e5dc50f8-c1de-4f26-8e83-64b1b3ea71d6"},{"name":"@performance_glitch_user","astNodeId":"53086390-d4fb-4c4f-bb4d-7e4a07fab550"}],"id":"saucedemo-loginsuccessful-login","steps":[{"arguments":[],"keyword":"Before","name":"","result":{"status":"passed","duration":1000000},"line":null,"match":{"location":"can not be determined with webdriver.io"}},{"arguments":[],"keyword":"Given","name":"user is on Saucedemo login page","result":{"status":"passed","duration":45000000},"line":null,"match":{"location":"can not be determined with webdriver.io"}},{"arguments":[],"keyword":"And","name":"user input password with \"secret_sauce\"","result":{"status":"passed","duration":122000000},"line":null,"match":{"location":"can not be determined with webdriver.io"}},{"arguments":[],"keyword":"Given","name":"user is on Saucedemo login page","result":{"status":"passed","duration":41000000},"line":null,"match":{"location":"can not be determined with webdriver.io"}},{"arguments":[],"keyword":"And","name":"user input username with \"problem_user\"","result":{"status":"passed","duration":154000000},"line":null,"match":{"location":"can not be determined with webdriver.io"}},{"arguments":[],"keyword":"When","name":"user click login button","result":{"status":"passed","duration":16000000},"line":null,"match":{"location":"can not be determined with webdriver.io"}},{"arguments":[],"keyword":"Then","name":"user should redirect to the homepage","result":{"status":"passed","duration":2012000000},"line":null,"match":{"location":"can not be determined with webdriver.io"}},{"arguments":[],"keyword":"After","name":"","result":{"status":"passed","duration":0},"line":null,"match":{"location":"can not be determined with webdriver.io"}}]},{"keyword":"Scenario","type":"scenario","description":"","name":"Successful login","tags":[{"name":"@saucedemo","astNodeId":"d00b2c75-cb22-4100-86a6-269c4198c8c0"},{"name":"@login","astNodeId":"1275352f-b79c-4c13-b6a6-ace34f97f6a7"},{"name":"@TC-1","astNodeId":"36d63fe4-8dfb-43be-9a96-0d9a21529788"},{"name":"@TC-2","astNodeId":"d7214667-7a50-4292-8c88-4507bbf92b32"},{"name":"@TC-3","astNodeId":"c0a5b1da-0d73-4a70-a01c-dd1012464efa"},{"name":"@TC-4","astNodeId":"d2437130-47fb-43ad-baf4-fb3a7ca7e427"},{"name":"@standard","astNodeId":"86e20412-6acf-4497-847f-c80e722e69cf"},{"name":"@visual","astNodeId":"3225c49b-9d0c-4b1f-beac-5e986a8fbbd5"},{"name":"@problem_user","astNodeId":"e5dc50f8-c1de-4f26-8e83-64b1b3ea71d6"},{"name":"@performance_glitch_user","astNodeId":"53086390-d4fb-4c4f-bb4d-7e4a07fab550"}],"id":"saucedemo-loginsuccessful-login","steps":[{"arguments":[],"keyword":"Before","name":"","result":{"status":"passed","duration":0},"line":null,"match":{"location":"can not be determined with webdriver.io"}},{"arguments":[],"keyword":"Given","name":"user is on Saucedemo login page","result":{"status":"passed","duration":36000000},"line":null,"match":{"location":"can not be determined with webdriver.io"}},{"arguments":[],"keyword":"And","name":"user input password with \"secret_sauce\"","result":{"status":"passed","duration":125000000},"line":null,"match":{"location":"can not be determined with webdriver.io"}},{"arguments":[],"keyword":"Given","name":"user is on Saucedemo login page","result":{"status":"passed","duration":36000000},"line":null,"match":{"location":"can not be determined with webdriver.io"}},{"arguments":[],"keyword":"And","name":"user input username with \"performance_glitc_user\"","result":{"status":"passed","duration":138000000},"line":null,"match":{"location":"can not be determined with webdriver.io"}},{"arguments":[],"keyword":"When","name":"user click login button","result":{"status":"passed","duration":14000000},"line":null,"match":{"location":"can not be determined with webdriver.io"}},{"arguments":[],"keyword":"Then","name":"user should redirect to the homepage","result":{"status":"passed","duration":2002000000},"line":null,"match":{"location":"can not be determined with webdriver.io"}},{"arguments":[],"keyword":"After","name":"","result":{"status":"passed","duration":0},"line":null,"match":{"location":"can not be determined with webdriver.io"}}]}],"id":"saucedemo-login","metadata":{"browser":{"name":"chrome","version":"126.0.6478.115"},"device":"Device name not known","platform":{"name":"windows","version":"Version not known"}}}]
