[{"keyword":"Feature","type":"feature","description":"","line":2,"name":"Saucedemo login","uri":"C:\\Users\\Yusuf\\Documents\\HAQIM\\Bootcamp QA\\QA\\wdio_cucumber_ds_batch4\\features\\saucedemo_login.feature","tags":[{"location":{"line":1,"column":1},"name":"@saucedemo","id":"49502e88-e6eb-4a11-a3de-e98a8f6c824d"},{"location":{"line":1,"column":12},"name":"@login","id":"a39126de-7ef7-45a5-8cce-5ff330771c07"}],"elements":[{"keyword":"Scenario","type":"scenario","description":"","name":"Successful login","tags":[{"name":"@saucedemo","astNodeId":"49502e88-e6eb-4a11-a3de-e98a8f6c824d"},{"name":"@login","astNodeId":"a39126de-7ef7-45a5-8cce-5ff330771c07"},{"name":"@TC-1","astNodeId":"0d946dcc-42b7-4a80-9c6a-2fe289a25f69"},{"name":"@TC-2","astNodeId":"ef21f8f1-fdd9-4166-b82a-bf94d5d07eb7"},{"name":"@TC-3","astNodeId":"feba014e-621e-4f8d-854b-29a24cc3f1d4"},{"name":"@TC-4","astNodeId":"b40ca693-792d-44af-9698-0572da616ade"},{"name":"@standard","astNodeId":"c235e1d9-a468-4811-b1ec-8ea7c9e2763d"},{"name":"@visual","astNodeId":"0e2fb7c7-dd31-4d05-b8e3-1d81ea13b2be"},{"name":"@problem_user","astNodeId":"f32c3a9c-8b02-4218-a688-ff8893929a0d"},{"name":"@performance_glitch_user","astNodeId":"209bd8ef-69d8-4689-99dd-00ca9ff08b84"}],"id":"saucedemo-loginsuccessful-login","steps":[{"arguments":[],"keyword":"Before","name":"","result":{"status":"passed","duration":4000000},"line":null,"match":{"location":"can not be determined with webdriver.io"}},{"arguments":[],"keyword":"Given","name":"user is on Saucedemo login page","result":{"status":"passed","duration":607000000},"line":null,"match":{"location":"can not be determined with webdriver.io"}},{"arguments":[],"keyword":"And","name":"user input password with \"secret_sauce\"","result":{"status":"passed","duration":250000000},"line":null,"match":{"location":"can not be determined with webdriver.io"}},{"arguments":[],"keyword":"Given","name":"user is on Saucedemo login page","result":{"status":"passed","duration":100000000},"line":null,"match":{"location":"can not be determined with webdriver.io"}},{"arguments":[],"keyword":"And","name":"user input username with \"standard_user\"","result":{"status":"passed","duration":243000000},"line":null,"match":{"location":"can not be determined with webdriver.io"}},{"arguments":[],"keyword":"When","name":"user click login button","result":{"status":"passed","duration":34000000},"line":null,"match":{"location":"can not be determined with webdriver.io"}},{"arguments":[],"keyword":"Then","name":"user should redirect to the homepage","result":{"status":"passed","duration":2016000000},"line":null,"match":{"location":"can not be determined with webdriver.io"}},{"arguments":[],"keyword":"After","name":"","result":{"status":"passed","duration":1000000},"line":null,"match":{"location":"can not be determined with webdriver.io"}}]},{"keyword":"Scenario","type":"scenario","description":"","name":"Successful login","tags":[{"name":"@saucedemo","astNodeId":"49502e88-e6eb-4a11-a3de-e98a8f6c824d"},{"name":"@login","astNodeId":"a39126de-7ef7-45a5-8cce-5ff330771c07"},{"name":"@TC-1","astNodeId":"0d946dcc-42b7-4a80-9c6a-2fe289a25f69"},{"name":"@TC-2","astNodeId":"ef21f8f1-fdd9-4166-b82a-bf94d5d07eb7"},{"name":"@TC-3","astNodeId":"feba014e-621e-4f8d-854b-29a24cc3f1d4"},{"name":"@TC-4","astNodeId":"b40ca693-792d-44af-9698-0572da616ade"},{"name":"@standard","astNodeId":"c235e1d9-a468-4811-b1ec-8ea7c9e2763d"},{"name":"@visual","astNodeId":"0e2fb7c7-dd31-4d05-b8e3-1d81ea13b2be"},{"name":"@problem_user","astNodeId":"f32c3a9c-8b02-4218-a688-ff8893929a0d"},{"name":"@performance_glitch_user","astNodeId":"209bd8ef-69d8-4689-99dd-00ca9ff08b84"}],"id":"saucedemo-loginsuccessful-login","steps":[{"arguments":[],"keyword":"Before","name":"","result":{"status":"passed","duration":1000000},"line":null,"match":{"location":"can not be determined with webdriver.io"}},{"arguments":[],"keyword":"Given","name":"user is on Saucedemo login page","result":{"status":"passed","duration":74000000},"line":null,"match":{"location":"can not be determined with webdriver.io"}},{"arguments":[],"keyword":"And","name":"user input password with \"secret_sauce\"","result":{"status":"passed","duration":180000000},"line":null,"match":{"location":"can not be determined with webdriver.io"}},{"arguments":[],"keyword":"Given","name":"user is on Saucedemo login page","result":{"status":"passed","duration":71000000},"line":null,"match":{"location":"can not be determined with webdriver.io"}},{"arguments":[],"keyword":"And","name":"user input username with \"visual_user\"","result":{"status":"passed","duration":184000000},"line":null,"match":{"location":"can not be determined with webdriver.io"}},{"arguments":[],"keyword":"When","name":"user click login button","result":{"status":"passed","duration":21000000},"line":null,"match":{"location":"can not be determined with webdriver.io"}},{"arguments":[],"keyword":"Then","name":"user should redirect to the homepage","result":{"status":"passed","duration":2015000000},"line":null,"match":{"location":"can not be determined with webdriver.io"}},{"arguments":[],"keyword":"After","name":"","result":{"status":"passed","duration":0},"line":null,"match":{"location":"can not be determined with webdriver.io"}}]},{"keyword":"Scenario","type":"scenario","description":"","name":"Successful login","tags":[{"name":"@saucedemo","astNodeId":"49502e88-e6eb-4a11-a3de-e98a8f6c824d"},{"name":"@login","astNodeId":"a39126de-7ef7-45a5-8cce-5ff330771c07"},{"name":"@TC-1","astNodeId":"0d946dcc-42b7-4a80-9c6a-2fe289a25f69"},{"name":"@TC-2","astNodeId":"ef21f8f1-fdd9-4166-b82a-bf94d5d07eb7"},{"name":"@TC-3","astNodeId":"feba014e-621e-4f8d-854b-29a24cc3f1d4"},{"name":"@TC-4","astNodeId":"b40ca693-792d-44af-9698-0572da616ade"},{"name":"@standard","astNodeId":"c235e1d9-a468-4811-b1ec-8ea7c9e2763d"},{"name":"@visual","astNodeId":"0e2fb7c7-dd31-4d05-b8e3-1d81ea13b2be"},{"name":"@problem_user","astNodeId":"f32c3a9c-8b02-4218-a688-ff8893929a0d"},{"name":"@performance_glitch_user","astNodeId":"209bd8ef-69d8-4689-99dd-00ca9ff08b84"}],"id":"saucedemo-loginsuccessful-login","steps":[{"arguments":[],"keyword":"Before","name":"","result":{"status":"passed","duration":0},"line":null,"match":{"location":"can not be determined with webdriver.io"}},{"arguments":[],"keyword":"Given","name":"user is on Saucedemo login page","result":{"status":"passed","duration":43000000},"line":null,"match":{"location":"can not be determined with webdriver.io"}},{"arguments":[],"keyword":"And","name":"user input password with \"secret_sauce\"","result":{"status":"passed","duration":185000000},"line":null,"match":{"location":"can not be determined with webdriver.io"}},{"arguments":[],"keyword":"Given","name":"user is on Saucedemo login page","result":{"status":"passed","duration":45000000},"line":null,"match":{"location":"can not be determined with webdriver.io"}},{"arguments":[],"keyword":"And","name":"user input username with \"problem_user\"","result":{"status":"passed","duration":185000000},"line":null,"match":{"location":"can not be determined with webdriver.io"}},{"arguments":[],"keyword":"When","name":"user click login button","result":{"status":"passed","duration":15000000},"line":null,"match":{"location":"can not be determined with webdriver.io"}},{"arguments":[],"keyword":"Then","name":"user should redirect to the homepage","result":{"status":"passed","duration":2017000000},"line":null,"match":{"location":"can not be determined with webdriver.io"}},{"arguments":[],"keyword":"After","name":"","result":{"status":"passed","duration":0},"line":null,"match":{"location":"can not be determined with webdriver.io"}}]},{"keyword":"Scenario","type":"scenario","description":"","name":"Successful login","tags":[{"name":"@saucedemo","astNodeId":"49502e88-e6eb-4a11-a3de-e98a8f6c824d"},{"name":"@login","astNodeId":"a39126de-7ef7-45a5-8cce-5ff330771c07"},{"name":"@TC-1","astNodeId":"0d946dcc-42b7-4a80-9c6a-2fe289a25f69"},{"name":"@TC-2","astNodeId":"ef21f8f1-fdd9-4166-b82a-bf94d5d07eb7"},{"name":"@TC-3","astNodeId":"feba014e-621e-4f8d-854b-29a24cc3f1d4"},{"name":"@TC-4","astNodeId":"b40ca693-792d-44af-9698-0572da616ade"},{"name":"@standard","astNodeId":"c235e1d9-a468-4811-b1ec-8ea7c9e2763d"},{"name":"@visual","astNodeId":"0e2fb7c7-dd31-4d05-b8e3-1d81ea13b2be"},{"name":"@problem_user","astNodeId":"f32c3a9c-8b02-4218-a688-ff8893929a0d"},{"name":"@performance_glitch_user","astNodeId":"209bd8ef-69d8-4689-99dd-00ca9ff08b84"}],"id":"saucedemo-loginsuccessful-login","steps":[{"arguments":[],"keyword":"Before","name":"","result":{"status":"passed","duration":0},"line":null,"match":{"location":"can not be determined with webdriver.io"}},{"arguments":[],"keyword":"Given","name":"user is on Saucedemo login page","result":{"status":"passed","duration":34000000},"line":null,"match":{"location":"can not be determined with webdriver.io"}},{"arguments":[],"keyword":"And","name":"user input password with \"secret_sauce\"","result":{"status":"passed","duration":115000000},"line":null,"match":{"location":"can not be determined with webdriver.io"}},{"arguments":[],"keyword":"Given","name":"user is on Saucedemo login page","result":{"status":"passed","duration":33000000},"line":null,"match":{"location":"can not be determined with webdriver.io"}},{"arguments":[],"keyword":"And","name":"user input username with \"performance_ghgh_user\"","result":{"status":"passed","duration":122000000},"line":null,"match":{"location":"can not be determined with webdriver.io"}},{"arguments":[],"keyword":"When","name":"user click login button","result":{"status":"passed","duration":16000000},"line":null,"match":{"location":"can not be determined with webdriver.io"}},{"arguments":[],"keyword":"Then","name":"user should redirect to the homepage","result":{"status":"passed","duration":2011000000},"line":null,"match":{"location":"can not be determined with webdriver.io"}},{"arguments":[],"keyword":"After","name":"","result":{"status":"passed","duration":1000000},"line":null,"match":{"location":"can not be determined with webdriver.io"}}]}],"id":"saucedemo-login","metadata":{"browser":{"name":"chrome","version":"126.0.6478.115"},"device":"Device name not known","platform":{"name":"windows","version":"Version not known"}}}]
